imgorient/__init__.py
imgorient/imgorient.py
imgorient/version.py
imgorient-1.0.0.dist-info/LICENSE
imgorient-1.0.0.dist-info/METADATA
imgorient-1.0.0.dist-info/WHEEL
imgorient-1.0.0.dist-info/entry_points.txt
imgorient-1.0.0.dist-info/RECORD
